itsyouonline/APIKeyLabel.py
itsyouonline/AddApiKeyReqBody.py
itsyouonline/AddIncludeSubOrgsOfReqBody.py
itsyouonline/AddOrganizationMemberReqBody.py
itsyouonline/Address.py
itsyouonline/Authorization.py
itsyouonline/AuthorizationMap.py
itsyouonline/Avatar.py
itsyouonline/BankAccount.py
itsyouonline/Company.py
itsyouonline/Contract.py
itsyouonline/ContractSigningRequest.py
itsyouonline/CreateGrantBody.py
itsyouonline/DigitalAssetAddress.py
itsyouonline/DigitalWalletAuthorization.py
itsyouonline/DnsAddress.py
itsyouonline/EmailAddress.py
itsyouonline/EnumJoinOrganizationInvitationMethod.py
itsyouonline/EnumJoinOrganizationInvitationRole.py
itsyouonline/EnumJoinOrganizationInvitationStatus.py
itsyouonline/Error.py
itsyouonline/FacebookAccount.py
itsyouonline/GetOrganizationUsersResponseBody.py
itsyouonline/GithubAccount.py
itsyouonline/Grant.py
itsyouonline/IsMember.py
itsyouonline/IyoID.py
itsyouonline/JoinOrganizationInvitation.py
itsyouonline/KeyData.py
itsyouonline/KeyStoreKey.py
itsyouonline/Label.py
itsyouonline/LocalizedInfoText.py
itsyouonline/Member.py
itsyouonline/Membership.py
itsyouonline/MissingScopes.py
itsyouonline/Notification.py
itsyouonline/Organization.py
itsyouonline/OrganizationAPIKey.py
itsyouonline/OrganizationLogo.py
itsyouonline/OrganizationTreeItem.py
itsyouonline/OrganizationUser.py
itsyouonline/Ownerof.py
itsyouonline/Party.py
itsyouonline/PhoneNumberValidation.py
itsyouonline/Phonenumber.py
itsyouonline/PublicKey.py
itsyouonline/RegistryEntry.py
itsyouonline/RequiredScope.py
itsyouonline/See.py
itsyouonline/SeeVersion.py
itsyouonline/SeeView.py
itsyouonline/SetOrgMemberReqBody.py
itsyouonline/SetOrgOwnerReqBody.py
itsyouonline/Signature.py
itsyouonline/TOTPSecret.py
itsyouonline/TwoFAMethods.py
itsyouonline/UpdateApIkeyReqBody.py
itsyouonline/UpdateGrantBody.py
itsyouonline/UpdateOrganizationApiKeyReqBody.py
itsyouonline/UpdateOrganizationOrgMemberShipReqBody.py
orgreviewer-0.0.1.dist-info/METADATA
orgreviewer-0.0.1.dist-info/RECORD
orgreviewer-0.0.1.dist-info/WHEEL
orgreviewer-0.0.1.dist-info/top_level.txt
