Metadata-Version: 2.1
Name: orgreviewer
Version: 0.0.1
Summary: A tool to manage users on itsyou.online
Home-page: UNKNOWN
Author: UNKNOWN
Author-email: UNKNOWN
License: UNKNOWN
Platform: UNKNOWN
Requires-Dist: click (==6.*)
Requires-Dist: pyyaml (==3.*)
Requires-Dist: requests (==2.*)
Requires-Dist: six (==1.*)
Requires-Dist: python-dateutil (==2.*)
